typey/__init__.py
typey/__main__.py
typey/challenge.py
typey/filecontroller.py
typey/typey.py
typey/assets/1-1000.txt
typey/assets/config.json
typey/assets/themes.json
Typey-1.0.4.dist-info/LICENSE
Typey-1.0.4.dist-info/METADATA
Typey-1.0.4.dist-info/WHEEL
Typey-1.0.4.dist-info/entry_points.txt
Typey-1.0.4.dist-info/top_level.txt
Typey-1.0.4.dist-info/RECORD
