Metadata-Version: 2.1
Name: Typey
Version: 1.0.4
Summary: A terminal typing test based on the likes of         monkeytype.gg and typings.gg, visualized with the blessed library.
Home-page: https://github.com/makemepresident/Typey
Author: makemepresident
License: GNU
Keywords: 10fastfingers,typeracer,typing test,typey,typing,typings,monkeytype,typingtest,type,keyboard,terminal,blessed,curses,mechanical keyboard
Platform: UNKNOWN
Classifier: Programming Language :: Python
Classifier: Topic :: Games/Entertainment
Classifier: Operating System :: Microsoft :: Windows
Classifier: Natural Language :: English
Classifier: License :: OSI Approved :: GNU General Public License v3 (GPLv3)
Classifier: Intended Audience :: End Users/Desktop
Classifier: Environment :: Console :: Curses
License-File: LICENSE
